siconfig
