Metadata-Version: 2.1
Name: siconfig
Version: 1.1
Summary: Simplified work with config files.
